[
  {
    "id": "scenario.abundant",
    "type": "scenario",
    "name": "Abundant Frontier",
    "info": "Rich, tightly-clustered deposits and a stocked spaceport buffer — a gentle first run.",
    "deposits": [
      "terrain.bauxite_deposit",
      "terrain.silica_quarry",
      "terrain.coal_seam",
      "terrain.titanium_deposit",
      "terrain.rare_earth_deposit",
      "terrain.oil_field"
    ],
    "patchSize": { "min": 4, "max": 5 },
    "spread": { "min": 6, "max": 18 },
    "startingKit": [{ "item": "item.rocket_fuel", "amount": 40 }],
    "startingTreasury": [
      { "item": "item.mining_drill", "amount": 6 },
      { "item": "item.oil_derrick", "amount": 2 },
      { "item": "item.smelter", "amount": 4 },
      { "item": "item.refinery", "amount": 2 },
      { "item": "item.chemical_plant", "amount": 2 },
      { "item": "item.composites_press", "amount": 1 },
      { "item": "item.rolling_mill", "amount": 2 },
      { "item": "item.electronics_bench", "amount": 2 },
      { "item": "item.machine_shop", "amount": 2 },
      { "item": "item.fabricator", "amount": 2 },
      { "item": "item.assembly_hall", "amount": 1 },
      { "item": "item.science_press", "amount": 1 },
      { "item": "item.aluminum", "amount": 120 },
      { "item": "item.aluminum_sheet", "amount": 24 },
      { "item": "item.microchip", "amount": 8 }
    ]
  },
  {
    "id": "scenario.sparse",
    "type": "scenario",
    "name": "Sparse Wastes",
    "info": "Small deposits scattered far and wide, with no starting buffer — a harder setup.",
    "deposits": [
      "terrain.bauxite_deposit",
      "terrain.silica_quarry",
      "terrain.coal_seam",
      "terrain.titanium_deposit",
      "terrain.rare_earth_deposit",
      "terrain.oil_field"
    ],
    "patchSize": { "min": 2, "max": 3 },
    "spread": { "min": 14, "max": 30 },
    "startingKit": [],
    "startingTreasury": [
      { "item": "item.mining_drill", "amount": 3 },
      { "item": "item.smelter", "amount": 2 },
      { "item": "item.refinery", "amount": 1 },
      { "item": "item.fabricator", "amount": 1 },
      { "item": "item.aluminum", "amount": 40 },
      { "item": "item.aluminum_sheet", "amount": 10 }
    ]
  }
]
